growingnn/__init__.py
growingnn/action.py
growingnn/config.py
growingnn/helpers.py
growingnn/optimizers.py
growingnn/painter.py
growingnn/quaziIdentity.py
growingnn/structure.py
growingnn/trainer.py
growingnn/Simulation/Qlearning_alg.py
growingnn/Simulation/__init__.py
growingnn/Simulation/greedy_alg.py
growingnn/Simulation/montecarlo_alg.py
growingnn/Simulation/random_alg.py
growingnn/Simulation/simulation.py
growingnn/Simulation/ScoreFunctions/SimulationScore.py
growingnn/Simulation/ScoreFunctions/__init__.py
growingnn/Simulation/ScoreFunctions/scoreByLearning.py
growingnn/Simulation/ScoreFunctions/scoreEfficiency.py
growingnn/Simulation/ScoreFunctions/scoreGraphStructure.py
growingnn-0.3.31.dist-info/LICENSE.txt
growingnn-0.3.31.dist-info/METADATA
growingnn-0.3.31.dist-info/WHEEL
growingnn-0.3.31.dist-info/top_level.txt
growingnn-0.3.31.dist-info/RECORD
