Metadata-Version: 2.1
Name: growingnn
Version: 0.3.31
Summary: growingnn is a cutting-edge Python package that introduces a dynamic neural network architecture learning algorithm. This innovative approach allows the neural network to adapt its structure during training, optimizing both weights and architecture. Leveraging a Stochastic Gradient Descent-based optimizer and guided Monte Carlo tree search, the package provides a powerful tool for enhancing model performance ICCS 2025 update.
Author: Szymon Świderski
Author-email: <szymonswiderski.ai@gmail.com>
License: MIT License
Keywords: python,neural network,growing neural network,growing
Classifier: Development Status :: 1 - Planning
Classifier: Intended Audience :: Developers
Classifier: Programming Language :: Python :: 3
Classifier: Operating System :: Unix
Classifier: Operating System :: MacOS :: MacOS X
Classifier: Operating System :: Microsoft :: Windows
License-File: LICENSE.txt
Requires-Dist: numpy
Requires-Dist: matplotlib
Requires-Dist: opencv-python
Requires-Dist: scipy
Requires-Dist: imgaug
Requires-Dist: scikit-learn
Requires-Dist: pyvis
